{
  "indexes": [
    {
      "collectionGroup": "users",
      "queryScope": "COLLECTION",
      "fields": [
        { "fieldPath": "isOnline", "order": "ASCENDING" },
        { "fieldPath": "stats.lastActive", "order": "DESCENDING" },
        { "fieldPath": "__name__", "order": "DESCENDING" }
      ]
    },
    {
      "collectionGroup": "blocked_users",
      "queryScope": "COLLECTION",
      "fields": [
        { "fieldPath": "blockerId", "order": "ASCENDING" },
        { "fieldPath": "blockedAt", "order": "DESCENDING" }
      ]
    }
  ],
  "fieldOverrides": []
}